configparsertool/__init__.py
configparsertool-1.0.2.dist-info/LICENSE
configparsertool-1.0.2.dist-info/METADATA
configparsertool-1.0.2.dist-info/WHEEL
configparsertool-1.0.2.dist-info/top_level.txt
configparsertool-1.0.2.dist-info/RECORD
