Metadata-Version: 2.1
Name: configparsertool
Version: 1.0.2
Summary: python configparser tool
Home-page: https://github.com/bjtj/python-configparser-tool
Author: bjtj
Author-email: bjtj10@gmail.com
License: UNKNOWN
Platform: UNKNOWN
Classifier: Programming Language :: Python :: 3
Classifier: License :: OSI Approved :: MIT License
Classifier: Operating System :: OS Independent
